Metadata-Version: 1.0
Name: funniestcxy
Version: 0.1
Summary: The funniest joke in the world
Home-page: http://github.com/storborg/funniest
Author: cxy
Author-email: crouchred@gmail.com
License: MIT
Platform: UNKNOWN
